learnergy/__init__.py
learnergy/core/__init__.py
learnergy/core/dataset.py
learnergy/core/model.py
learnergy/math/__init__.py
learnergy/math/metrics.py
learnergy/math/scale.py
learnergy/models/__init__.py
learnergy/models/bernoulli/__init__.py
learnergy/models/bernoulli/conv_rbm.py
learnergy/models/bernoulli/discriminative_rbm.py
learnergy/models/bernoulli/dropout_rbm.py
learnergy/models/bernoulli/e_dropout_rbm.py
learnergy/models/bernoulli/rbm.py
learnergy/models/deep/__init__.py
learnergy/models/deep/conv_dbn.py
learnergy/models/deep/dbn.py
learnergy/models/deep/residual_dbn.py
learnergy/models/extra/__init__.py
learnergy/models/extra/sigmoid_rbm.py
learnergy/models/gaussian/__init__.py
learnergy/models/gaussian/gaussian_conv_rbm.py
learnergy/models/gaussian/gaussian_rbm.py
learnergy/utils/__init__.py
learnergy/utils/constants.py
learnergy/utils/exception.py
learnergy/utils/logging.py
learnergy/visual/__init__.py
learnergy/visual/convergence.py
learnergy/visual/image.py
learnergy/visual/tensor.py
learnergy-1.1.4.dist-info/LICENSE
learnergy-1.1.4.dist-info/METADATA
learnergy-1.1.4.dist-info/WHEEL
learnergy-1.1.4.dist-info/top_level.txt
learnergy-1.1.4.dist-info/RECORD
