Metadata-Version: 2.1
Name: learnergy
Version: 1.1.4
Summary: Energy-based Machine Learners
Home-page: https://github.com/gugarosa/learnergy
Author: Mateus Roder and Gustavo de Rosa
Author-email: mateus.roder@unesp.br, gustavo.rosa@unesp.br
License: Apache 2.0
Classifier: Development Status :: 5 - Production/Stable
Classifier: Intended Audience :: Developers
Classifier: Intended Audience :: Education
Classifier: Intended Audience :: Science/Research
Classifier: License :: OSI Approved :: Apache Software License
Classifier: Programming Language :: Python :: 3.6
Classifier: Programming Language :: Python :: 3.7
Classifier: Programming Language :: Python :: 3.8
Classifier: Programming Language :: Python :: 3.9
Classifier: Topic :: Software Development :: Libraries
Classifier: Topic :: Software Development :: Libraries :: Python Modules
License-File: LICENSE
Requires-Dist: matplotlib (>=3.3.4)
Requires-Dist: Pillow (>=8.1.2)
Requires-Dist: pre-commit (>=2.17.0)
Requires-Dist: requests (>2.23.0)
Requires-Dist: scikit-image (>=0.17.2)
Requires-Dist: torch (>=1.8.0)
Requires-Dist: torchvision (>=0.9.0)
Requires-Dist: tqdm (>=4.49.0)
Provides-Extra: tests
Requires-Dist: coverage ; extra == 'tests'
Requires-Dist: pylint ; extra == 'tests'
Requires-Dist: pytest ; extra == 'tests'
Requires-Dist: pytest-pep8 ; extra == 'tests'
